{
    "name" : "FW/1 Commands",
    "slug" : "fw1-commands",
    "version" : "2.0.0",
    "author" : "Tony Junkes - @cfchef",
    "location" : "https://github.com/framework-one/fw1-commands/archive/master.zip",
    "Homepage" : "https://github.com/framework-one/fw1-commands",
    "Documentation" : "https://github.com/framework-one/fw1-commands/blob/master/README.md",
    "Repository" : {
        "type" : "git", "URL" : "https://github.com/framework-one/fw1-commands.git"
    },
    "Bugs" : "https://github.com/framework-one/fw1-commands/issues",
    "shortDescription" : "A collection of CommandBox commands for FW/1.",
    "description" : "A collection of CommandBox commands for FW/1.",
    "instructions" : "https://github.com/framework-one/fw1-commands/blob/master/README.md",
    "changelog" : "https://github.com/framework-one/fw1-commands/commits/master",
    "type" : "commandbox-modules",
    "keywords" : [ "fw1", "framework one", "commandbox", "commands" ],
    "private" : "false",
    "License" : [
        { "type" : "MIT" }
    ],
    "Contributors" : [ {"name": "Contributors List", "url": "https://github.com/framework-one/fw1-commands/graphs/contributors"} ],
    "ignore" : [ "*.md", "*.txt" ]
}
